somosmas_common/__init__.py
somosmas_common/authentication_backends.py
somosmas_common/graphql.py
somosmas_common/middlewares.py
somosmas_common-1.0.5.dist-info/METADATA
somosmas_common-1.0.5.dist-info/RECORD
somosmas_common-1.0.5.dist-info/WHEEL
somosmas_common-1.0.5.dist-info/top_level.txt
